setup.py
scrap_gushiwen_authors/__init__.py
scrap_gushiwen_authors/scrap_gushiwen_authors.py
scrap_gushiwen_authors.egg-info/PKG-INFO
scrap_gushiwen_authors.egg-info/SOURCES.txt
scrap_gushiwen_authors.egg-info/dependency_links.txt
scrap_gushiwen_authors.egg-info/top_level.txt