Metadata-Version: 1.0
Name: scrap-gushiwen-authors
Version: 1.0
Summary: Search the authors of gushiwen.
Home-page: https://scratch.mit.edu/users/jiu12/
Author: David Bagel
Author-email: jiuprogrammer@gmail.com
License: UNKNOWN
Platform: UNKNOWN
